zstarfile/__init__.py
zstarfile/extra.py
zstarfile/py.typed
zstarfile/tarfile.py
zstarfile-0.3.0.dist-info/licenses/LICENSE
zstarfile-0.3.0.dist-info/WHEEL
zstarfile-0.3.0.dist-info/METADATA
zstarfile-0.3.0.dist-info/RECORD
