Metadata-Version: 2.4
Name: zstarfile
Version: 0.3.0
Summary: tarfile extension with additional compression algorithms and PEP 706 by default
Author-email: Maxwell G <maxwell@gtmx.me>
Requires-Python: >=3.9
Classifier: License :: OSI Approved :: MIT License
Classifier: Programming Language :: Python :: 3
Classifier: Programming Language :: Python :: 3 :: Only
Classifier: Programming Language :: Python :: 3.9
Classifier: Programming Language :: Python :: 3.10
Classifier: Programming Language :: Python :: 3.11
Classifier: Programming Language :: Python :: 3.12
Classifier: Programming Language :: Python :: 3.13
Classifier: Programming Language :: Python :: 3.14
Classifier: Development Status :: 3 - Alpha
Classifier: Typing :: Typed
License-File: LICENSE
Requires-Dist: zstarfile[lz4] ; extra == "all"
Requires-Dist: zstarfile[zstandard] ; extra == "all"
Requires-Dist: pymarkdownlnt ; extra == "codeqa"
Requires-Dist: ruff>=0.2.0 ; extra == "codeqa"
Requires-Dist: reuse ; extra == "codeqa"
Requires-Dist: zstarfile[codeqa] ; extra == "dev"
Requires-Dist: zstarfile[formatters] ; extra == "dev"
Requires-Dist: zstarfile[test] ; extra == "dev"
Requires-Dist: zstarfile[typing] ; extra == "dev"
Requires-Dist: nox ; extra == "dev"
Requires-Dist: black ; extra == "formatters"
Requires-Dist: isort ; extra == "formatters"
Requires-Dist: lz4 ; extra == "lz4"
Requires-Dist: zstarfile[all] ; extra == "test"
Requires-Dist: pytest ; extra == "test"
Requires-Dist: zstarfile[all] ; extra == "typing"
Requires-Dist: mypy ; extra == "typing"
Requires-Dist: pytest ; extra == "typing"
Requires-Dist: typing_extensions ; extra == "typing"
Requires-Dist: nox ; extra == "typing"
Requires-Dist: pyzstd ; extra == "zstandard"
Project-URL: Changelog, https://git.sr.ht/~gotmax23/zstarfile/tree/main/item/NEWS.md
Project-URL: Homepage, https://sr.ht/~gotmax23/zstarfile
Project-URL: Mailing List, https://lists.sr.ht/~gotmax23/zstarfile
Project-URL: Source, https://git.sr.ht/~gotmax23/zstarfile
Provides-Extra: all
Provides-Extra: codeqa
Provides-Extra: dev
Provides-Extra: formatters
Provides-Extra: lz4
Provides-Extra: test
Provides-Extra: typing
Provides-Extra: zstandard
